stitchem/__init__.py
stitchem/align/benchmark.py
stitchem/align/bruteforce.py
stitchem/align/match_template.py
stitchem/align/orb.py
stitchem/align/phase_cross_correlation.py
stitchem/cli.py
stitchem/conversion.py
stitchem/io.py
stitchem/stitch.py
stitchem-0.2.1.dist-info/WHEEL
stitchem-0.2.1.dist-info/entry_points.txt
stitchem-0.2.1.dist-info/METADATA
stitchem-0.2.1.dist-info/RECORD
