Metadata-Version: 2.3
Name: stitchem
Version: 0.2.1
Summary: Fast image stitching to convert areascan images to linescan images.
Author: roel klein
Author-email: roel klein <roel.klein@wur.nl>
Requires-Dist: click>=8.3.1
Requires-Dist: numba>=0.63.1
Requires-Dist: opencv-python>=4.12.0.88
Requires-Dist: scikit-image>=0.26.0
Requires-Dist: tqdm>=4.67.1
Requires-Python: >=3.12
